LICENSE
MANIFEST.in
README.md
requirements.txt
setup.cfg
setup.py
gcdt_slack_integration/__init__.py
gcdt_slack_integration/slack.py
gcdt_slack_integration.egg-info/PKG-INFO
gcdt_slack_integration.egg-info/SOURCES.txt
gcdt_slack_integration.egg-info/dependency_links.txt
gcdt_slack_integration.egg-info/entry_points.txt
gcdt_slack_integration.egg-info/requires.txt
gcdt_slack_integration.egg-info/top_level.txt